{
    "H-": "⠁",
    "P-": "⠂",
    "PH-": "⠃",
    "T-": "⠄",
    "TH-": "⠅",
    "TP-": "⠆",
    "TPH-": "⠇",
    "-F": "⠈",
    "H-F": "⠉",
    "P-F": "⠊",
    "PH-F": "⠋",
    "T-F": "⠌",
    "TH-F": "⠍",
    "TP-F": "⠎",
    "TPH-F": "⠏",
    "-P": "⠐",
    "H-P": "⠑",
    "P-P": "⠒",
    "PH-P": "⠓",
    "T-P": "⠔",
    "TH-P": "⠕",
    "TP-P": "⠖",
    "TPH-P": "⠗",
    "-FP": "⠘",
    "H-FP": "⠙",
    "P-FP": "⠚",
    "PH-FP": "⠛",
    "T-FP": "⠜",
    "TH-FP": "⠝",
    "TP-FP": "⠞",
    "TPH-FP": "⠟",
    "-L": "⠠",
    "H-L": "⠡",
    "P-L": "⠢",
    "PH-L": "⠣",
    "T-L": "⠤",
    "TH-L": "⠥",
    "TP-L": "⠦",
    "TPH-L": "⠧",
    "-FL": "⠨",
    "H-FL": "⠩",
    "P-FL": "⠪",
    "PH-FL": "⠫",
    "T-FL": "⠬",
    "TH-FL": "⠭",
    "TP-FL": "⠮",
    "TPH-FL": "⠯",
    "-PL": "⠰",
    "H-PL": "⠱",
    "P-PL": "⠲",
    "PH-PL": "⠳",
    "T-PL": "⠴",
    "TH-PL": "⠵",
    "TP-PL": "⠶",
    "TPH-PL": "⠷",
    "-FPL": "⠸",
    "H-FPL": "⠹",
    "P-FPL": "⠺",
    "PH-FPL": "⠻",
    "T-FPL": "⠼",
    "TH-FPL": "⠽",
    "TP-FPL": "⠾",
    "TPH-FPL": "⠿"
}